h5dict/__init__.py
h5dict/conversions.py
h5dict/h5dict.py
h5dict-0.2.3.dist-info/METADATA
h5dict-0.2.3.dist-info/WHEEL
h5dict-0.2.3.dist-info/top_level.txt
h5dict-0.2.3.dist-info/RECORD
