Metadata-Version: 2.1
Name: h5dict
Version: 0.2.3
Summary: An interface to read/write HDF5 files as if they where dictionaries.
Home-page: https://nanogennari.gitlab.io/h5dict/
Author: nano
Author-email: me@nngn.net
License: UNKNOWN
Platform: UNKNOWN
Classifier: Development Status :: 4 - Beta
Classifier: Programming Language :: Python :: 3
Classifier: License :: OSI Approved :: GNU General Public License v3 (GPLv3)
Classifier: Operating System :: OS Independent
Requires-Python: >=3.6
Requires-Dist: h5py (>=3.0)
